slapddgen.py
slapddgen-0.1.1.dist-info/METADATA
slapddgen-0.1.1.dist-info/RECORD
slapddgen-0.1.1.dist-info/WHEEL
slapddgen-0.1.1.dist-info/entry_points.txt
slapddgen-0.1.1.dist-info/top_level.txt
