Metadata-Version: 2.1
Name: slapddgen
Version: 0.1.1
Summary: slapd.d generator
Home-page: https://github.com/daenney/slapddgen
Author: Daniele Sluijters
Author-email: daenney@users.noreply.github.com
License: UNKNOWN
Platform: UNKNOWN
Classifier: Development Status :: 3 - Alpha
Classifier: Environment :: Console
Classifier: Intended Audience :: System Administrators
Classifier: License :: OSI Approved :: MIT License
Classifier: Operating System :: POSIX
Classifier: Programming Language :: Python :: 3.7
Classifier: Programming Language :: Python :: 3 :: Only
Classifier: Topic :: System :: Systems Administration :: Authentication/Directory :: LDAP
Classifier: Topic :: Utilities
Requires-Dist: Click
Requires-Dist: jinja2
